pump_portal_mcp_server/__init__.py
pump_portal_mcp_server/server.py
pump_portal_mcp_server/config/__init__.py
pump_portal_mcp_server/config/constants.py
pump_portal_mcp_server/config/settings.py
pump_portal_mcp_server/core/__init__.py
pump_portal_mcp_server/core/exceptions.py
pump_portal_mcp_server/core/progress_tracker.py
pump_portal_mcp_server/core/server.py
pump_portal_mcp_server/core/validation.py
pump_portal_mcp_server/prompts/__init__.py
pump_portal_mcp_server/prompts/trading.py
pump_portal_mcp_server/resources/__init__.py
pump_portal_mcp_server/resources/operation_status.py
pump_portal_mcp_server/resources/wallet_info.py
pump_portal_mcp_server/services/__init__.py
pump_portal_mcp_server/services/portal_client.py
pump_portal_mcp_server/services/trading_service.py
pump_portal_mcp_server/tools/__init__.py
pump_portal_mcp_server/tools/check_balance.py
pump_portal_mcp_server/tools/claim_fees.py
pump_portal_mcp_server/tools/create_token.py
pump_portal_mcp_server/tools/create_wallet.py
pump_portal_mcp_server/tools/trading.py
pump_portal_mcp_server/utils/__init__.py
pump_portal_mcp_server/utils/logging_utils.py
pump_portal_mcp_server/utils/validation_utils.py
pump_portal_mcp_server-3.0.2.dist-info/METADATA
pump_portal_mcp_server-3.0.2.dist-info/WHEEL
pump_portal_mcp_server-3.0.2.dist-info/entry_points.txt
pump_portal_mcp_server-3.0.2.dist-info/RECORD
